cornerstone_widget/__init__.py
cornerstone_widget/_version.py
cornerstone_widget/cs_widget.py
cornerstone_widget/utils.py
cornerstone_widget/static/extension.js
cornerstone_widget/static/index.js
cornerstone_widget/static/index.js.map
cornerstone_widget-0.0.1rc1.data/data/etc/jupyter/nbconfig/notebook.d/cornerstone_widget.json
cornerstone_widget-0.0.1rc1.data/data/share/jupyter/nbextensions/cornerstone_widget/extension.js
cornerstone_widget-0.0.1rc1.data/data/share/jupyter/nbextensions/cornerstone_widget/index.js
cornerstone_widget-0.0.1rc1.data/data/share/jupyter/nbextensions/cornerstone_widget/index.js.map
cornerstone_widget-0.0.1rc1.dist-info/METADATA
cornerstone_widget-0.0.1rc1.dist-info/RECORD
cornerstone_widget-0.0.1rc1.dist-info/WHEEL
cornerstone_widget-0.0.1rc1.dist-info/top_level.txt
